{
    "Tables": {
        "Page 5": {
            "Header": [
                "Carton,Order No,Part Number,Description,Unit Price,Qty,Sales Value,Customs Value"
            ],
            "Rows": [
                [
                    "9.32,1,9.32,9.32,2401-629,K181953/1,A-5004-7608,M4 ACC SWIVEL ,L1-13.,Country of Origin: UNITED KINGDOM,90319000,Commodity Code,Export CPC    10 00 001"
                ],
                [
                    "47.49,1,47.49,47.49,2401-629,K181953/1,A-5103-4370,XM POWER SUPPLY ,KIT,Country of Origin: UNITED KINGDOM,85044095,Commodity Code,Export CPC    10 00 001, ,It is confirmed that this item is not controlled/ dual use"
                ],
                [
                    "38.01,4,152.04,152.04,2401-643,K181955,A-5000-3626,M2 STR D2 5BALL ,L19.,Country of Origin: UNITED KINGDOM,90319000,Commodity Code,Export CPC    10 00 001"
                ],
                [
                    "18.39,2,36.78,36.78,2401-643,K181955,A-5000-7792,M4 ACC CENTRE ,5WAY,Country of Origin: UNITED KINGDOM,90319000,Commodity Code,Export CPC    10 00 001"
                ],
                [
                    "15.20,5,76.00,76.00,2401-643,K181955,A-5000-7808,M2 STY D1R L20 ,EWL7,Country of Origin: UNITED KINGDOM,90319000,Commodity Code,Export CPC    10 00 001"
                ],
                [
                    "26.77,6,160.62,160.62,2401-643,K181955,A-5000-8156,M4 STY D6R L150 ,EWL1,Country of Origin: UNITED KINGDOM,90319000,Commodity Code,Export CPC    10 00 001"
                ],
                [
                    "21.89,2,43.78,43.78,2401-643,K181955,A-5003-0044,M2 STY D4R L40 ,EWL40,Country of Origin: UNITED KINGDOM,90319000,Commodity Code,Export CPC    10 00 001"
                ],
                [
                    "18.68,2,37.36,37.36,2401-643,K181955,A-5003-0052,M3 STY D2R L30 ,EWL22,Country of Origin: UNITED KINGDOM,90319000,Commodity Code,Export CPC    10 00 001"
                ],
                [
                    "21.89,2,43.78,43.78,2401-643,K181955,A-5003-0058,M3 STY D3R L40 ,EWL33,Country of Origin: UNITED KINGDOM,90319000,Commodity Code,Export CPC    10 00 001"
                ],
                [
                    "21.89,2,43.78,43.78,2401-643,K181955,A-5003-0061,M3 STY D4R L50 ,EWL46,Country of Origin: UNITED KINGDOM,90319000,Commodity Code,Export CPC    10 00 001"
                ]
            ]
        }
    },
    "Metadata": {
        "format": "PDF 1.7",
        "title": "GBWLCommercial.rpt v1.19",
        "creator": "Crystal Reports",
        "producer": "Powered By Crystal",
        "creationDate": "D:20240105151255+05'30'",
        "modDate": "D:20250225161817+05'30'"
    }
}